<annotation>
	<folder>Roya</folder>
	<filename>roya (6).jpg</filename>
	<path>C:\Users\Julio Ríos\Desktop\Plagas de Café\Roya\roya (6).jpg</path>
	<source>
		<database>Unknown</database>
	</source>
	<size>
		<width>1024</width>
		<height>683</height>
		<depth>3</depth>
	</size>
	<segmented>0</segmented>
	<object>
		<name>roya</name>
		<pose>Unspecified</pose>
		<truncated>0</truncated>
		<difficult>0</difficult>
		<bndbox>
			<xmin>328</xmin>
			<ymin>323</ymin>
			<xmax>761</xmax>
			<ymax>560</ymax>
		</bndbox>
	</object>
</annotation>
